stegnet/__init__.py
stegnet/__main__.py
stegnet/cli.py
stegnet/core/__init__.py
stegnet/core/encryption.py
stegnet/core/packet_utils.py
stegnet/core/steg_base.py
stegnet/core/traffic_analysis.py
stegnet/protocols/__init__.py
stegnet/protocols/dns.py
stegnet/protocols/http.py
stegnet/protocols/icmp.py
stegnet/protocols/tcp.py
stegnet-1.0.2.dist-info/entry_points.txt
stegnet-1.0.2.dist-info/LICENSE
stegnet-1.0.2.dist-info/METADATA
stegnet-1.0.2.dist-info/WHEEL
stegnet-1.0.2.dist-info/RECORD
